LICENSE
MANIFEST.in
README.rst
requirements.txt
setup.cfg
setup.py
test-requirements.txt
push_test/__init__.py
push_test/__main__.py
push_test/pushclient.py
push_test.egg-info/PKG-INFO
push_test.egg-info/SOURCES.txt
push_test.egg-info/dependency_links.txt
push_test.egg-info/entry_points.txt
push_test.egg-info/not-zip-safe
push_test.egg-info/requires.txt
push_test.egg-info/top_level.txt
push_test/tests/__init__.py
push_test/tests/test_pushclient.py