Metadata-Version: 1.1
Name: push-test
Version: 0.1.1
Summary: Autopush Smoke Test
Home-page: UNKNOWN
Author: JR Conlin
Author-email: jr+src@mozilla.com
License: MPL2
Keywords: autopush test
Platform: UNKNOWN
Classifier: Topic :: Internet :: WWW/HTTP
Classifier: Programming Language :: Python
Classifier: Programming Language :: Python :: 3.5
Classifier: Programming Language :: Python :: 3.6
